exchange/InstrumentExchangesHolder.py
exchange/__init__.py
exchange/rate/ExchangeRateHolder.py
exchange/rate/InstantRate.py
exchange/rate/__init__.py
persuader_technology_automata_exchange-0.1.8.dist-info/LICENSE
persuader_technology_automata_exchange-0.1.8.dist-info/METADATA
persuader_technology_automata_exchange-0.1.8.dist-info/WHEEL
persuader_technology_automata_exchange-0.1.8.dist-info/top_level.txt
persuader_technology_automata_exchange-0.1.8.dist-info/RECORD
